Flask_Prose-0.1.56.dist-info/DESCRIPTION.rst
Flask_Prose-0.1.56.dist-info/METADATA
Flask_Prose-0.1.56.dist-info/RECORD
Flask_Prose-0.1.56.dist-info/WHEEL
Flask_Prose-0.1.56.dist-info/metadata.json
Flask_Prose-0.1.56.dist-info/top_level.txt
flask_prose/__init__.py
flask_prose/engine.py
flask_prose/fsqla_storage.py
flask_prose/models.py
flask_prose/prosemaker.py
flask_prose/storage.py
flask_prose/views.py
tests/__init__.py
tests/_test_proseapi_security.py
tests/prosetestcase.py
tests/security_models.py
tests/storage.py
tests/storage_test_methods.py
tests/storage_test_tables.py
tests/test_proseapi.py
tests/test_prosemaker.py
tests/test_sqlite_storage.py
