Metadata-Version: 2.0
Name: Flask-Prose
Version: 0.1.56
Summary: A flask extension for generating markov prose
Home-page: https://github.com/slippers/Flask-Prose
Author: Kirk Erickson
Author-email: ekirk0@gmail.com
License: MIT
Platform: any
Classifier: Development Status :: 3 - Alpha
Classifier: Environment :: Web Environment
Classifier: Framework :: Flask
Classifier: Intended Audience :: Developers
Classifier: License :: OSI Approved :: MIT License
Classifier: Operating System :: OS Independent
Classifier: Programming Language :: Python
Classifier: Programming Language :: Python :: 2
Classifier: Programming Language :: Python :: 2.7
Classifier: Programming Language :: Python :: 3
Classifier: Programming Language :: Python :: 3.4
Classifier: Topic :: Internet :: WWW/HTTP :: Dynamic Content
Classifier: Topic :: Software Development :: Libraries :: Python Modules
Requires-Dist: click (==6.7)
Requires-Dist: flask-jsontools-slippers (==0.1.6)
Requires-Dist: flask-sqlalchemy (==2.2)
Requires-Dist: flask (==0.12.1)
Requires-Dist: itsdangerous (==0.24)
Requires-Dist: jinja2 (==2.9.6)
Requires-Dist: markovify (==0.6.0)
Requires-Dist: markupsafe (==1.0)
Requires-Dist: six (==1.10.0)
Requires-Dist: sqlalchemy-utils (==0.32.14)
Requires-Dist: sqlalchemy (==1.1.10)
Requires-Dist: textstat (==0.3.1)
Requires-Dist: unidecode (==0.4.20)
Requires-Dist: werkzeug (==0.12.1)
